<?xml version="1.0"?>
<whoisapi>
  <response>
    <domain_name>copy.com</domain_name>
    <ip_history>
      <domain>COPY.COM</domain>
      <post_ip>205.196.223.24</post_ip>
      <pre_ip/>
      <action>N</action>
      <actiondate>2006-02-13</actiondate>
      <action_in_words>New</action_in_words>
    </ip_history>
    <ip_history>
      <domain>COPY.COM</domain>
      <post_ip>72.3.135.150</post_ip>
      <pre_ip>205.196.223.24</pre_ip>
      <action>C</action>
      <actiondate>2007-05-27</actiondate>
      <action_in_words>Change</action_in_words>
    </ip_history>
    <ip_history>
      <domain>COPY.COM</domain>
      <post_ip/>
      <pre_ip>72.3.135.150</pre_ip>
      <action>D</action>
      <actiondate>2007-10-21</actiondate>
      <action_in_words>Not Resolvable</action_in_words>
    </ip_history>
    <ip_history>
      <domain>COPY.COM</domain>
      <post_ip/>
      <pre_ip>72.3.135.150</pre_ip>
      <action>D</action>
      <actiondate>2007-10-21</actiondate>
      <action_in_words>Not Resolvable</action_in_words>
    </ip_history>
    <ip_history>
      <domain>COPY.COM</domain>
      <post_ip>205.178.189.131</post_ip>
      <pre_ip>72.3.135.150</pre_ip>
      <action>C</action>
      <actiondate>2008-03-20</actiondate>
      <action_in_words>Change</action_in_words>
    </ip_history>
    <ip_history>
      <domain>COPY.COM</domain>
      <post_ip>209.62.20.200</post_ip>
      <pre_ip>205.178.189.131</pre_ip>
      <action>C</action>
      <actiondate>2008-07-06</actiondate>
      <action_in_words>Change</action_in_words>
    </ip_history>
    <ip_history>
      <domain>COPY.COM</domain>
      <post_ip>205.178.189.131</post_ip>
      <pre_ip>209.62.20.200</pre_ip>
      <action>C</action>
      <actiondate>2009-02-16</actiondate>
      <action_in_words>Change</action_in_words>
    </ip_history>
    <ip_history>
      <domain>COPY.COM</domain>
      <post_ip>69.46.228.182</post_ip>
      <pre_ip>205.178.189.131</pre_ip>
      <action>C</action>
      <actiondate>2009-04-13</actiondate>
      <action_in_words>Change</action_in_words>
    </ip_history>
    <ip_history>
      <domain>COPY.COM</domain>
      <post_ip>208.73.210.26</post_ip>
      <pre_ip>69.46.228.182</pre_ip>
      <action>C</action>
      <actiondate>2009-07-06</actiondate>
      <action_in_words>Change</action_in_words>
    </ip_history>
    <ip_history>
      <domain>COPY.COM</domain>
      <post_ip>208.73.210.27</post_ip>
      <pre_ip>208.73.210.26</pre_ip>
      <action>C</action>
      <actiondate>2009-07-27</actiondate>
      <action_in_words>Change</action_in_words>
    </ip_history>
    <ip_history>
      <domain>COPY.COM</domain>
      <post_ip>208.73.210.28</post_ip>
      <pre_ip>208.73.210.27</pre_ip>
      <action>C</action>
      <actiondate>2010-06-02</actiondate>
      <action_in_words>Change</action_in_words>
    </ip_history>
    <ip_history>
      <domain>COPY.COM</domain>
      <post_ip>208.73.210.29</post_ip>
      <pre_ip>208.73.210.28</pre_ip>
      <action>C</action>
      <actiondate>2010-10-04</actiondate>
      <action_in_words>Change</action_in_words>
    </ip_history>
    <ip_history>
      <domain>COPY.COM</domain>
      <post_ip>204.14.49.180</post_ip>
      <pre_ip>208.73.210.29</pre_ip>
      <action>C</action>
      <actiondate>2011-03-23</actiondate>
      <action_in_words>Change</action_in_words>
    </ip_history>
    <ip_history>
      <domain>COPY.COM</domain>
      <post_ip>204.14.49.180</post_ip>
      <pre_ip/>
      <action>N</action>
      <actiondate>2011-04-10</actiondate>
      <action_in_words>New</action_in_words>
    </ip_history>
    <ip_history>
      <domain>COPY.COM</domain>
      <post_ip/>
      <pre_ip>204.14.49.180</pre_ip>
      <action>D</action>
      <actiondate>2011-08-23</actiondate>
      <action_in_words>Not Resolvable</action_in_words>
    </ip_history>
    <ip_history>
      <domain>COPY.COM</domain>
      <post_ip>64.235.150.73</post_ip>
      <pre_ip/>
      <action>N</action>
      <actiondate>2011-09-18</actiondate>
      <action_in_words>New</action_in_words>
    </ip_history>
    <ip_history>
      <domain>COPY.COM</domain>
      <post_ip>64.235.151.4</post_ip>
      <pre_ip>64.235.150.73</pre_ip>
      <action>C</action>
      <actiondate>2011-12-11</actiondate>
      <action_in_words>Change</action_in_words>
    </ip_history>
    <ip_history>
      <domain>COPY.COM</domain>
      <post_ip>64.235.154.138</post_ip>
      <pre_ip>64.235.151.4</pre_ip>
      <action>C</action>
      <actiondate>2013-02-06</actiondate>
      <action_in_words>Change</action_in_words>
    </ip_history>
    <ip_history>
      <domain>COPY.COM</domain>
      <post_ip>64.235.151.4</post_ip>
      <pre_ip>64.235.154.138</pre_ip>
      <action>C</action>
      <actiondate>2013-02-17</actiondate>
      <action_in_words>Change</action_in_words>
    </ip_history>
    <ip_history>
      <domain>COPY.COM</domain>
      <post_ip>64.235.151.9</post_ip>
      <pre_ip>64.235.151.4</pre_ip>
      <action>C</action>
      <actiondate>2013-03-11</actiondate>
      <action_in_words>Change</action_in_words>
    </ip_history>
    <ip_history>
      <domain>COPY.COM</domain>
      <post_ip>64.235.151.4</post_ip>
      <pre_ip>64.235.151.9</pre_ip>
      <action>C</action>
      <actiondate>2013-04-03</actiondate>
      <action_in_words>Change</action_in_words>
    </ip_history>
    <ip_history>
      <domain>COPY.COM</domain>
      <post_ip>64.235.151.9</post_ip>
      <pre_ip>64.235.151.4</pre_ip>
      <action>C</action>
      <actiondate>2013-04-14</actiondate>
      <action_in_words>Change</action_in_words>
    </ip_history>
    <ip_history>
      <domain>COPY.COM</domain>
      <post_ip>64.235.151.4</post_ip>
      <pre_ip>64.235.151.9</pre_ip>
      <action>C</action>
      <actiondate>2013-04-26</actiondate>
      <action_in_words>Change</action_in_words>
    </ip_history>
    <ip_history>
      <domain>COPY.COM</domain>
      <post_ip>64.235.151.9</post_ip>
      <pre_ip>64.235.151.4</pre_ip>
      <action>C</action>
      <actiondate>2013-06-24</actiondate>
      <action_in_words>Change</action_in_words>
    </ip_history>
    <ip_history>
      <domain>COPY.COM</domain>
      <post_ip>64.235.151.4</post_ip>
      <pre_ip>64.235.151.9</pre_ip>
      <action>C</action>
      <actiondate>2013-07-06</actiondate>
      <action_in_words>Change</action_in_words>
    </ip_history>
    <ip_history>
      <domain>COPY.COM</domain>
      <post_ip>64.235.151.9</post_ip>
      <pre_ip>64.235.151.4</pre_ip>
      <action>C</action>
      <actiondate>2013-07-19</actiondate>
      <action_in_words>Change</action_in_words>
    </ip_history>
    <ip_history>
      <domain>COPY.COM</domain>
      <post_ip>64.235.151.4</post_ip>
      <pre_ip>64.235.151.9</pre_ip>
      <action>C</action>
      <actiondate>2013-07-31</actiondate>
      <action_in_words>Change</action_in_words>
    </ip_history>
    <ip_history>
      <domain>COPY.COM</domain>
      <post_ip>64.235.151.9</post_ip>
      <pre_ip>64.235.151.4</pre_ip>
      <action>C</action>
      <actiondate>2013-08-12</actiondate>
      <action_in_words>Change</action_in_words>
    </ip_history>
    <ip_history>
      <domain>COPY.COM</domain>
      <post_ip>64.235.151.4</post_ip>
      <pre_ip>64.235.151.9</pre_ip>
      <action>C</action>
      <actiondate>2013-09-06</actiondate>
      <action_in_words>Change</action_in_words>
    </ip_history>
    <ip_history>
      <domain>COPY.COM</domain>
      <post_ip>64.235.151.9</post_ip>
      <pre_ip>64.235.151.4</pre_ip>
      <action>C</action>
      <actiondate>2013-10-24</actiondate>
      <action_in_words>Change</action_in_words>
    </ip_history>
    <ip_history>
      <domain>COPY.COM</domain>
      <post_ip>64.235.151.4</post_ip>
      <pre_ip>64.235.151.9</pre_ip>
      <action>C</action>
      <actiondate>2013-12-01</actiondate>
      <action_in_words>Change</action_in_words>
    </ip_history>
    <ip_history>
      <domain>COPY.COM</domain>
      <post_ip>64.235.151.9</post_ip>
      <pre_ip>64.235.151.4</pre_ip>
      <action>C</action>
      <actiondate>2013-12-30</actiondate>
      <action_in_words>Change</action_in_words>
    </ip_history>
    <ip_history>
      <domain>COPY.COM</domain>
      <post_ip>64.235.151.4</post_ip>
      <pre_ip>64.235.151.9</pre_ip>
      <action>C</action>
      <actiondate>2014-01-12</actiondate>
      <action_in_words>Change</action_in_words>
    </ip_history>
    <ip_history>
      <domain>COPY.COM</domain>
      <post_ip>64.235.151.9</post_ip>
      <pre_ip>64.235.151.4</pre_ip>
      <action>C</action>
      <actiondate>2014-01-25</actiondate>
      <action_in_words>Change</action_in_words>
    </ip_history>
    <ip_history>
      <domain>COPY.COM</domain>
      <post_ip>64.235.151.4</post_ip>
      <pre_ip>64.235.151.9</pre_ip>
      <action>C</action>
      <actiondate>2014-02-20</actiondate>
      <action_in_words>Change</action_in_words>
    </ip_history>
    <ip_history>
      <domain>COPY.COM</domain>
      <post_ip>64.235.151.9</post_ip>
      <pre_ip>64.235.151.4</pre_ip>
      <action>C</action>
      <actiondate>2014-04-28</actiondate>
      <action_in_words>Change</action_in_words>
    </ip_history>
    <ip_history>
      <domain>COPY.COM</domain>
      <post_ip>64.235.151.4</post_ip>
      <pre_ip>64.235.151.9</pre_ip>
      <action>C</action>
      <actiondate>2014-05-10</actiondate>
      <action_in_words>Change</action_in_words>
    </ip_history>
    <ip_history>
      <domain>COPY.COM</domain>
      <post_ip>64.235.151.9</post_ip>
      <pre_ip>64.235.151.4</pre_ip>
      <action>C</action>
      <actiondate>2014-06-03</actiondate>
      <action_in_words>Change</action_in_words>
    </ip_history>
    <ip_history>
      <domain>COPY.COM</domain>
      <post_ip>64.235.151.4</post_ip>
      <pre_ip>64.235.151.9</pre_ip>
      <action>C</action>
      <actiondate>2014-06-15</actiondate>
      <action_in_words>Change</action_in_words>
    </ip_history>
    <ip_history>
      <domain>COPY.COM</domain>
      <post_ip>64.235.151.9</post_ip>
      <pre_ip>64.235.151.4</pre_ip>
      <action>C</action>
      <actiondate>2014-06-27</actiondate>
      <action_in_words>Change</action_in_words>
    </ip_history>
    <ip_history>
      <domain>COPY.COM</domain>
      <post_ip>64.235.151.4</post_ip>
      <pre_ip>64.235.151.9</pre_ip>
      <action>C</action>
      <actiondate>2014-07-09</actiondate>
      <action_in_words>Change</action_in_words>
    </ip_history>
    <ip_history>
      <domain>COPY.COM</domain>
      <post_ip>64.235.151.9</post_ip>
      <pre_ip>64.235.151.4</pre_ip>
      <action>C</action>
      <actiondate>2014-07-21</actiondate>
      <action_in_words>Change</action_in_words>
    </ip_history>
    <ip_history>
      <domain>COPY.COM</domain>
      <post_ip>64.235.151.4</post_ip>
      <pre_ip>64.235.151.9</pre_ip>
      <action>C</action>
      <actiondate>2014-08-02</actiondate>
      <action_in_words>Change</action_in_words>
    </ip_history>
    <ip_history>
      <domain>COPY.COM</domain>
      <post_ip>64.235.151.9</post_ip>
      <pre_ip>64.235.151.4</pre_ip>
      <action>C</action>
      <actiondate>2014-08-26</actiondate>
      <action_in_words>Change</action_in_words>
    </ip_history>
    <ip_history>
      <domain>COPY.COM</domain>
      <post_ip>64.235.151.4</post_ip>
      <pre_ip>64.235.151.9</pre_ip>
      <action>C</action>
      <actiondate>2014-09-20</actiondate>
      <action_in_words>Change</action_in_words>
    </ip_history>
    <ip_history>
      <domain>COPY.COM</domain>
      <post_ip>64.235.151.9</post_ip>
      <pre_ip>64.235.151.4</pre_ip>
      <action>C</action>
      <actiondate>2014-10-02</actiondate>
      <action_in_words>Change</action_in_words>
    </ip_history>
    <ip_history>
      <domain>COPY.COM</domain>
      <post_ip>64.235.151.4</post_ip>
      <pre_ip>64.235.151.9</pre_ip>
      <action>C</action>
      <actiondate>2014-10-14</actiondate>
      <action_in_words>Change</action_in_words>
    </ip_history>
    <ip_history>
      <domain>COPY.COM</domain>
      <post_ip>64.235.151.9</post_ip>
      <pre_ip>64.235.151.4</pre_ip>
      <action>C</action>
      <actiondate>2014-10-27</actiondate>
      <action_in_words>Change</action_in_words>
    </ip_history>
    <ip_history>
      <domain>COPY.COM</domain>
      <post_ip>64.235.151.4</post_ip>
      <pre_ip>64.235.151.9</pre_ip>
      <action>C</action>
      <actiondate>2014-11-09</actiondate>
      <action_in_words>Change</action_in_words>
    </ip_history>
    <ip_history>
      <domain>COPY.COM</domain>
      <post_ip>64.235.151.9</post_ip>
      <pre_ip>64.235.151.4</pre_ip>
      <action>C</action>
      <actiondate>2015-01-26</actiondate>
      <action_in_words>Change</action_in_words>
    </ip_history>
    <ip_history>
      <domain>COPY.COM</domain>
      <post_ip>64.235.151.4</post_ip>
      <pre_ip>64.235.151.9</pre_ip>
      <action>C</action>
      <actiondate>2015-02-08</actiondate>
      <action_in_words>Change</action_in_words>
    </ip_history>
    <ip_history>
      <domain>COPY.COM</domain>
      <post_ip>64.235.151.9</post_ip>
      <pre_ip>64.235.151.4</pre_ip>
      <action>C</action>
      <actiondate>2015-02-21</actiondate>
      <action_in_words>Change</action_in_words>
    </ip_history>
    <ip_history>
      <domain>COPY.COM</domain>
      <post_ip>64.235.151.4</post_ip>
      <pre_ip>64.235.151.9</pre_ip>
      <action>C</action>
      <actiondate>2015-04-02</actiondate>
      <action_in_words>Change</action_in_words>
    </ip_history>
    <ip_history>
      <domain>COPY.COM</domain>
      <post_ip>64.235.151.9</post_ip>
      <pre_ip>64.235.151.4</pre_ip>
      <action>C</action>
      <actiondate>2015-04-15</actiondate>
      <action_in_words>Change</action_in_words>
    </ip_history>
    <ip_history>
      <domain>COPY.COM</domain>
      <post_ip>64.235.151.4</post_ip>
      <pre_ip>64.235.151.9</pre_ip>
      <action>C</action>
      <actiondate>2015-04-28</actiondate>
      <action_in_words>Change</action_in_words>
    </ip_history>
    <ip_history>
      <domain>COPY.COM</domain>
      <post_ip>64.235.151.9</post_ip>
      <pre_ip>64.235.151.4</pre_ip>
      <action>C</action>
      <actiondate>2015-05-11</actiondate>
      <action_in_words>Change</action_in_words>
    </ip_history>
    <ip_history>
      <domain>COPY.COM</domain>
      <post_ip>64.235.151.4</post_ip>
      <pre_ip>64.235.151.9</pre_ip>
      <action>C</action>
      <actiondate>2015-05-25</actiondate>
      <action_in_words>Change</action_in_words>
    </ip_history>
    <ip_history>
      <domain>COPY.COM</domain>
      <post_ip>64.235.151.9</post_ip>
      <pre_ip>64.235.151.4</pre_ip>
      <action>C</action>
      <actiondate>2015-06-08</actiondate>
      <action_in_words>Change</action_in_words>
    </ip_history>
    <ip_history>
      <domain>COPY.COM</domain>
      <post_ip>64.235.151.4</post_ip>
      <pre_ip>64.235.151.9</pre_ip>
      <action>C</action>
      <actiondate>2015-08-04</actiondate>
      <action_in_words>Change</action_in_words>
    </ip_history>
    <registrar_history>
      <domain>COPY.COM</domain>
      <date_updated>2001-11-05</date_updated>
      <date_created>1995-02-16</date_created>
      <date_expires>2010-02-17</date_expires>
      <date_lastchecked>2004-10-07</date_lastchecked>
      <registrar>Network Solutions</registrar>
      <registrartag>Network Solutions</registrartag>
    </registrar_history>
    <registrar_history>
      <domain>COPY.COM</domain>
      <date_updated>2009-12-28</date_updated>
      <date_created>1995-02-16</date_created>
      <date_expires>2012-02-17</date_expires>
      <date_lastchecked>2010-01-20</date_lastchecked>
      <registrar>Fabulous.com</registrar>
      <registrartag>FABULOUS.COM PTY LTD.</registrartag>
    </registrar_history>
    <registrar_history>
      <domain>COPY.COM</domain>
      <date_updated>2011-06-29</date_updated>
      <date_created>1995-02-16</date_created>
      <date_expires>2013-02-17</date_expires>
      <date_lastchecked>2011-07-20</date_lastchecked>
      <registrar>eNom.com</registrar>
      <registrartag>ENOM, INC.</registrartag>
    </registrar_history>
    <registrar_history>
      <domain>COPY.COM</domain>
      <date_updated>2012-04-06</date_updated>
      <date_created>1995-02-16</date_created>
      <date_expires>2014-02-17</date_expires>
      <date_lastchecked>2012-04-20</date_lastchecked>
      <registrar>BearsDomain</registrar>
      <registrartag>BEARSDOMAIN, LLC</registrartag>
    </registrar_history>
    <registrar_history>
      <domain>COPY.COM</domain>
      <date_updated>2012-04-06</date_updated>
      <date_created>1995-02-16</date_created>
      <date_expires>2014-02-17</date_expires>
      <date_lastchecked>2012-05-20</date_lastchecked>
      <registrar>Domain.com, LLC</registrar>
      <registrartag>DOMAIN.COM, LLC</registrartag>
    </registrar_history>
    <nameserver_history>
      <domain>COPY.COM</domain>
      <action>T</action>
      <actiondate>2006-02-13</actiondate>
      <action_in_words>Transfer</action_in_words>
      <post_mns>Dreamhost.com</post_mns>
      <pre_mns>Seanet.com</pre_mns>
    </nameserver_history>
    <nameserver_history>
      <domain>COPY.COM</domain>
      <action>T</action>
      <actiondate>2008-03-20</actiondate>
      <action_in_words>Transfer</action_in_words>
      <post_mns>Worldnic.com</post_mns>
      <pre_mns>Dreamhost.com</pre_mns>
    </nameserver_history>
    <nameserver_history>
      <domain>COPY.COM</domain>
      <action>T</action>
      <actiondate>2008-06-29</actiondate>
      <action_in_words>Transfer</action_in_words>
      <post_mns>Islandnet.com</post_mns>
      <pre_mns>Worldnic.com</pre_mns>
    </nameserver_history>
    <nameserver_history>
      <domain>COPY.COM</domain>
      <action>T</action>
      <actiondate>2008-07-01</actiondate>
      <action_in_words>Transfer</action_in_words>
      <post_mns>Worldnic.com</post_mns>
      <pre_mns>Islandnet.com</pre_mns>
    </nameserver_history>
    <nameserver_history>
      <domain>COPY.COM</domain>
      <action>T</action>
      <actiondate>2009-04-10</actiondate>
      <action_in_words>Transfer</action_in_words>
      <post_mns>Parked.com</post_mns>
      <pre_mns>Worldnic.com</pre_mns>
    </nameserver_history>
    <nameserver_history>
      <domain>COPY.COM</domain>
      <action>T</action>
      <actiondate>2009-06-15</actiondate>
      <action_in_words>Transfer</action_in_words>
      <post_mns>Worldnic.com</post_mns>
      <pre_mns>Parked.com</pre_mns>
    </nameserver_history>
    <nameserver_history>
      <domain>COPY.COM</domain>
      <action>T</action>
      <actiondate>2009-06-18</actiondate>
      <action_in_words>Transfer</action_in_words>
      <post_mns>Parked.com</post_mns>
      <pre_mns>Worldnic.com</pre_mns>
    </nameserver_history>
    <nameserver_history>
      <domain>COPY.COM</domain>
      <action>T</action>
      <actiondate>2009-06-30</actiondate>
      <action_in_words>Transfer</action_in_words>
      <post_mns>Dsredirection.com</post_mns>
      <pre_mns>Parked.com</pre_mns>
    </nameserver_history>
    <nameserver_history>
      <domain>COPY.COM</domain>
      <action>T</action>
      <actiondate>2011-03-23</actiondate>
      <action_in_words>Transfer</action_in_words>
      <post_mns>Dnsmadeeasy.com</post_mns>
      <pre_mns>Dsredirection.com</pre_mns>
    </nameserver_history>
    <nameserver_history>
      <domain>COPY.COM</domain>
      <action>T</action>
      <actiondate>2011-08-17</actiondate>
      <action_in_words>Transfer</action_in_words>
      <post_mns>Dynect.net</post_mns>
      <pre_mns>Dnsmadeeasy.com</pre_mns>
    </nameserver_history>
    <nameserver_history>
      <domain>COPY.COM</domain>
      <action>T</action>
      <actiondate>2015-07-02</actiondate>
      <action_in_words>Transfer</action_in_words>
      <post_mns>Verisigndns.com</post_mns>
      <pre_mns>Dynect.net</pre_mns>
    </nameserver_history>
  </response>
</whoisapi>

