<?xml version="1.0"?>
<whoisapi>
  <response>
    <domain_name>webssearches.com</domain_name>
    <ip_history>
      <domain>WEBSSEARCHES.COM</domain>
      <post_ip>69.28.57.29</post_ip>
      <pre_ip/>
      <action>N</action>
      <actiondate>2013-07-31</actiondate>
      <action_in_words>New</action_in_words>
    </ip_history>
    <ip_history>
      <domain>WEBSSEARCHES.COM</domain>
      <post_ip>69.28.58.54</post_ip>
      <pre_ip>69.28.57.29</pre_ip>
      <action>C</action>
      <actiondate>2013-08-12</actiondate>
      <action_in_words>Change</action_in_words>
    </ip_history>
    <ip_history>
      <domain>WEBSSEARCHES.COM</domain>
      <post_ip>184.173.136.124</post_ip>
      <pre_ip>69.28.58.54</pre_ip>
      <action>C</action>
      <actiondate>2013-10-24</actiondate>
      <action_in_words>Change</action_in_words>
    </ip_history>
    <ip_history>
      <domain>WEBSSEARCHES.COM</domain>
      <post_ip>69.28.58.38</post_ip>
      <pre_ip>184.173.136.124</pre_ip>
      <action>C</action>
      <actiondate>2014-01-12</actiondate>
      <action_in_words>Change</action_in_words>
    </ip_history>
    <ip_history>
      <domain>WEBSSEARCHES.COM</domain>
      <post_ip>69.28.57.22</post_ip>
      <pre_ip>69.28.58.38</pre_ip>
      <action>C</action>
      <actiondate>2014-11-09</actiondate>
      <action_in_words>Change</action_in_words>
    </ip_history>
    <registrar_history>
      <domain>WEBSSEARCHES.COM</domain>
      <date_updated>2013-07-17</date_updated>
      <date_created>2013-07-17</date_created>
      <date_expires>2014-07-17</date_expires>
      <date_lastchecked>2013-07-18</date_lastchecked>
      <registrar>GoDaddy.com</registrar>
      <registrartag>Go Daddy Software Inc</registrartag>
    </registrar_history>
    <nameserver_history>
      <domain>WEBSSEARCHES.COM</domain>
      <action>N</action>
      <actiondate>2013-07-18</actiondate>
      <action_in_words>New</action_in_words>
      <post_mns>Domaincontrol.com</post_mns>
      <pre_mns/>
    </nameserver_history>
  </response>
</whoisapi>

