<?xml version="1.0"?>
<whoisapi>
  <response>
    <registrant>Plentyoffish Media Inc</registrant>
    <registration>
      <created>2012-04-25</created>
      <updated>2012-04-25</updated>
    </registration>
    <whois>
      <date>2015-08-05</date>
      <record>NetRange:       199.182.216.0 - 199.182.219.255
CIDR:           199.182.216.0/22
NetName:        POF-RANGE-1
NetHandle:      NET-199-182-216-0-1
Parent:         NET199 (NET-199-0-0-0-0)
NetType:        Direct Assignment
OriginAS:       AS54652
Organization:   Plentyoffish Media Inc (PM-32)
RegDate:        2012-04-25
Updated:        2012-04-25
Ref:            http://whois.arin.net/rest/net/NET-199-182-216-0-1

OrgName:        Plentyoffish Media Inc
OrgId:          PM-32
Address:        555 W Hastings St, Suite 2525
City:           Vancouver
StateProv:      BC
PostalCode:     V6B 4N5
Country:        CA
RegDate:        2011-12-27
Updated:        2014-03-19
Ref:            http://whois.arin.net/rest/org/PM-32

OrgNOCHandle: NETWO4773-ARIN
OrgNOCName:   Network Admin
OrgNOCPhone:  +1-778-373-0957 
OrgNOCEmail:  network-admin@pof.com
OrgNOCRef:    http://whois.arin.net/rest/poc/NETWO4773-ARIN

OrgAbuseHandle: NETWO4773-ARIN
OrgAbuseName:   Network Admin
OrgAbusePhone:  +1-778-373-0957 
OrgAbuseEmail:  network-admin@pof.com
OrgAbuseRef:    http://whois.arin.net/rest/poc/NETWO4773-ARIN

OrgTechHandle: NETWO4773-ARIN
OrgTechName:   Network Admin
OrgTechPhone:  +1-778-373-0957 
OrgTechEmail:  network-admin@pof.com
OrgTechRef:    http://whois.arin.net/rest/poc/NETWO4773-ARIN</record>
    </whois>
  </response>
</whoisapi>

