<?xml version="1.0"?>
<whoisapi>
  <response>
    <registrant>The Home Depot Inc.</registrant>
    <registration>
      <created>1995-12-14</created>
      <updated>2014-10-01</updated>
    </registration>
    <whois>
      <date>2015-08-05</date>
      <record>NetRange:       207.11.0.0 - 207.11.127.255
CIDR:           207.11.0.0/17
NetName:        HOMEDEPOT-BLK
NetHandle:      NET-207-11-0-0-1
Parent:         NET207 (NET-207-0-0-0-0)
NetType:        Direct Assignment
OriginAS:       
Organization:   The Home Depot Inc. (THEHOM)
RegDate:        1995-12-14
Updated:        2014-10-01
Ref:            http://whois.arin.net/rest/net/NET-207-11-0-0-1

OrgName:        The Home Depot Inc.
OrgId:          THEHOM
Address:        2455 Paces Ferry Road
City:           Atlanta
StateProv:      GA
PostalCode:     30339
Country:        US
RegDate:        1993-06-07
Updated:        2014-08-06
Ref:            http://whois.arin.net/rest/org/THEHOM

OrgTechHandle: NETWO3288-ARIN
OrgTechName:   Network Services
OrgTechPhone:  +1-770-319-2311 
OrgTechEmail:  domain_administrator@homedepot.com
OrgTechRef:    http://whois.arin.net/rest/poc/NETWO3288-ARIN

OrgAbuseHandle: NETWO3288-ARIN
OrgAbuseName:   Network Services
OrgAbusePhone:  +1-770-319-2311 
OrgAbuseEmail:  domain_administrator@homedepot.com
OrgAbuseRef:    http://whois.arin.net/rest/poc/NETWO3288-ARIN

RTechHandle: NETWO3288-ARIN
RTechName:   Network Services
RTechPhone:  +1-770-319-2311 
RTechEmail:  domain_administrator@homedepot.com
RTechRef:    http://whois.arin.net/rest/poc/NETWO3288-ARIN</record>
    </whois>
  </response>
</whoisapi>

