<?xml version="1.0"?>
<whoisapi>
  <response>
    <registrant>SWITCH, LTD</registrant>
    <registration>
      <created>2012-09-07</created>
      <updated>2015-05-14</updated>
    </registration>
    <whois>
      <date>2015-08-05</date>
      <record>NetRange:       136.179.0.0 - 136.179.255.255
CIDR:           136.179.0.0/16
NetName:        SWITCH-LTD
NetHandle:      NET-136-179-0-0-1
Parent:         NET136 (NET-136-0-0-0-0)
NetType:        Direct Allocation
OriginAS:       
Organization:   SWITCH, LTD (SWITC-2)
RegDate:        2012-09-07
Updated:        2015-05-14
Ref:            http://whois.arin.net/rest/net/NET-136-179-0-0-1

OrgName:        SWITCH, LTD
OrgId:          SWITC-2
Address:        7135 South Decatur Blvd
City:           Las Vegas
StateProv:      NV
PostalCode:     89118
Country:        US
RegDate:        2005-02-24
Updated:        2015-05-14
Ref:            http://whois.arin.net/rest/org/SWITC-2

OrgNOCHandle: NOC1746-ARIN
OrgNOCName:   NOC
OrgNOCPhone:  +1-702-444-4000 
OrgNOCEmail:  noc@switchnap.com
OrgNOCRef:    http://whois.arin.net/rest/poc/NOC1746-ARIN

OrgAbuseHandle: ABUSE860-ARIN
OrgAbuseName:   Abuse
OrgAbusePhone:  +1-702-444-4000 
OrgAbuseEmail:  abuse@switchnap.com
OrgAbuseRef:    http://whois.arin.net/rest/poc/ABUSE860-ARIN

OrgTechHandle: NETOP119-ARIN
OrgTechName:   netops
OrgTechPhone:  +1-702-333-6602 
OrgTechEmail:  netops@switchnap.com
OrgTechRef:    http://whois.arin.net/rest/poc/NETOP119-ARIN

RAbuseHandle: ABUSE860-ARIN
RAbuseName:   Abuse
RAbusePhone:  +1-702-444-4000 
RAbuseEmail:  abuse@switchnap.com
RAbuseRef:    http://whois.arin.net/rest/poc/ABUSE860-ARIN

RTechHandle: NETOP119-ARIN
RTechName:   netops
RTechPhone:  +1-702-333-6602 
RTechEmail:  netops@switchnap.com
RTechRef:    http://whois.arin.net/rest/poc/NETOP119-ARIN

RNOCHandle: NOC1746-ARIN
RNOCName:   NOC
RNOCPhone:  +1-702-444-4000 
RNOCEmail:  noc@switchnap.com
RNOCRef:    http://whois.arin.net/rest/poc/NOC1746-ARIN

NetRange:       136.179.236.0 - 136.179.239.255
CIDR:           136.179.236.0/22
NetName:        SHUTTERFLY-236
NetHandle:      NET-136-179-236-0-1
Parent:         SWITCH-LTD (NET-136-179-0-0-1)
NetType:        Reallocated
OriginAS:       AS26447
Organization:   Shutterfly, Inc. (SHUTT)
RegDate:        2014-02-27
Updated:        2014-02-27
Comment:        Static downstream customer allocation
Ref:            http://whois.arin.net/rest/net/NET-136-179-236-0-1

OrgName:        Shutterfly, Inc.
OrgId:          SHUTT
Address:        2800 Bridge Parkway
City:           Redwood City
StateProv:      CA
PostalCode:     94065
Country:        US
RegDate:        2002-08-28
Updated:        2011-09-24
Ref:            http://whois.arin.net/rest/org/SHUTT

OrgAbuseHandle: ATC2-ARIN
OrgAbuseName:   ARIN Technical Contact
OrgAbusePhone:  +1-650-610-5200 
OrgAbuseEmail:  arin-tech@shutterfly.com
OrgAbuseRef:    http://whois.arin.net/rest/poc/ATC2-ARIN

OrgTechHandle: ATC2-ARIN
OrgTechName:   ARIN Technical Contact
OrgTechPhone:  +1-650-610-5200 
OrgTechEmail:  arin-tech@shutterfly.com
OrgTechRef:    http://whois.arin.net/rest/poc/ATC2-ARIN</record>
    </whois>
  </response>
</whoisapi>

